{"assets":{"49DD6E1C21B4EE3F8ED4E2262884C007":{"type":"texture","index":55,"assetRequest":{"type":"slide","state":"incoming","slide":"75E6FE96-A7D9-45DA-9C3E-68F1D812F73F"},"url":{"web":"assets/49DD6E1C21B4EE3F8ED4E2262884C007.svg"},"width":1920,"height":1080},"DBF86B2DB036C9E4A2B62AFAD9A94124":{"type":"texture","index":54,"assetRequest":{"type":"slide","state":"outgoing","slide":"9EF75D75-B1F8-4504-9EF6-3B8C1714DE38"},"url":{"web":"assets/DBF86B2DB036C9E4A2B62AFAD9A94124.svg"},"width":1920,"height":1080}},"events":[{"effects":[{"beginTime":0,"baseLayer":{"animations":[],"initialState":{"affineTransform":[1,0,0,1,0,0],"masksToBounds":false,"rotation":0,"scale":1,"position":{"pointX":960,"pointY":540},"width":1920,"sublayerTransform":[1,0,0,0,0,1,0,0,0,0,1,0,0,0,0,1],"contentsRect":{"y":0,"x":0,"width":1,"height":1},"opacity":1,"edgeAntialiasingMask":251658240,"height":1080,"hidden":false,"anchorPoint":{"pointX":0.5,"pointY":0.5}},"objectID":"0","layers":[{"animations":[],"initialState":{"affineTransform":[1,0,0,1,0,0],"masksToBounds":false,"rotation":0,"scale":1,"position":{"pointX":960,"pointY":540},"width":1920,"sublayerTransform":[1,0,0,0,0,1,0,0,0,0,1,-0.0003500791246677598,0,0,0,1],"contentsRect":{"y":0,"x":0,"width":1,"height":1},"opacity":1,"edgeAntialiasingMask":251658240,"height":1080,"hidden":false,"anchorPoint":{"pointX":0.5,"pointY":0.5}},"layers":[{"animations":[],"layers":[],"initialState":{"affineTransform":[1,0,0,1,0,0],"masksToBounds":false,"rotation":0,"scale":1,"position":{"pointX":960,"pointY":540},"width":1920,"sublayerTransform":[1,0,0,0,0,1,0,0,0,0,1,0,0,0,0,1],"contentsRect":{"y":0,"x":0,"width":1,"height":1},"opacity":1,"edgeAntialiasingMask":0,"height":1080,"hidden":false,"anchorPoint":{"pointX":0.5,"pointY":0.5}},"texture":"49DD6E1C21B4EE3F8ED4E2262884C007"},{"animations":[{"timeOffset":0,"from":{"scalar":false},"beginTime":0,"repeatCount":0,"fillMode":"both","property":"hidden","autoreverses":false,"duration":0.01,"to":{"scalar":true}}],"layers":[],"initialState":{"affineTransform":[1,0,0,1,0,0],"masksToBounds":false,"rotation":0,"scale":1,"position":{"pointX":960,"pointY":540},"width":1920,"sublayerTransform":[1,0,0,0,0,1,0,0,0,0,1,0,0,0,0,1],"contentsRect":{"y":0,"x":0,"width":1,"height":1},"opacity":1,"edgeAntialiasingMask":0,"height":1080,"hidden":false,"anchorPoint":{"pointX":0.5,"pointY":0.5}},"texture":"DBF86B2DB036C9E4A2B62AFAD9A94124"}]}]},"effects":[],"duration":0.01,"type":"transition","name":"none","objectID":"0"}],"automaticPlay":false,"hyperlinks":[],"accessibility":[{"text":"pasted-image.pdf","targetRectangle":{"y":488.8765869140625,"x":70.7626953125,"width":1778.474609375,"height":102.2467956542969}},{"text":"Time Series","targetRectangle":{"y":337.9962909221649,"x":786.7617049217224,"width":272.376,"height":64.43362426757812}},{"text":"Key and Data Design","targetRectangle":{"y":104,"x":506.1999999999999,"width":907.6000000000003,"height":118.0993041992188}},{"text":".provider.network.limelight.231","targetRectangle":{"y":667.1827516555786,"x":244.4226787352562,"width":584.3199999999999,"height":47.8397216796875}},{"text":".2,2,1,2,2","targetRectangle":{"y":667.9014196395874,"x":1744.213013207912,"width":166.8000000000002,"height":47.8397216796875}},{"text":"Screen Shot 2016-02-16 at 12.05.28 AM.png","targetRectangle":{"y":707.0927085876465,"x":474.1689671874046,"width":31.92657470703125,"height":29.93116188049316}},{"text":"buffer_event","targetRectangle":{"y":666.4917602539062,"x":5.763624780178048,"width":236.64,"height":47.8397216796875}},{"text":".1455570114342 ","targetRectangle":{"y":667.9014196395874,"x":827.5068401122094,"width":309.2449999999999,"height":48.51904296875}},{"text":".[country=US,state=OR,client=ipad]","targetRectangle":{"y":667.1827540397644,"x":1130.813810937405,"width":610.6399999999999,"height":47.8397216796875}}],"baseLayer":{"animations":[],"initialState":{"affineTransform":[1,0,0,1,0,0],"masksToBounds":false,"rotation":0,"scale":1,"position":{"pointX":960,"pointY":540},"width":1920,"sublayerTransform":[1,0,0,0,0,1,0,0,0,0,1,0,0,0,0,1],"contentsRect":{"y":0,"x":0,"width":1,"height":1},"opacity":1,"edgeAntialiasingMask":251658240,"height":1080,"hidden":false,"anchorPoint":{"pointX":0.5,"pointY":0.5}},"objectID":"0","layers":[{"animations":[],"initialState":{"affineTransform":[1,0,0,1,0,0],"masksToBounds":false,"rotation":0,"scale":1,"position":{"pointX":960,"pointY":540},"width":1920,"sublayerTransform":[1,0,0,0,0,1,0,0,0,0,1,-0.0003500791246677598,0,0,0,1],"contentsRect":{"y":0,"x":0,"width":1,"height":1},"opacity":1,"edgeAntialiasingMask":251658240,"height":1080,"hidden":false,"anchorPoint":{"pointX":0.5,"pointY":0.5}},"layers":[{"animations":[],"layers":[],"initialState":{"affineTransform":[1,0,0,1,0,0],"masksToBounds":false,"rotation":0,"scale":1,"position":{"pointX":960,"pointY":540},"width":1920,"sublayerTransform":[1,0,0,0,0,1,0,0,0,0,1,0,0,0,0,1],"contentsRect":{"y":0,"x":0,"width":1,"height":1},"opacity":1,"edgeAntialiasingMask":0,"height":1080,"hidden":false,"anchorPoint":{"pointX":0.5,"pointY":0.5}},"texture":"DBF86B2DB036C9E4A2B62AFAD9A94124"}]}]}}]}